authapi/__init__.py
authapi/app.py
authapi/data.py
authapi/providers/__init__.py
authapi/providers/facebook/__init__.py
authapi/providers/facebook/facebook.py
authapi/providers/facebook/instagram.py
authapi/providers/facebook/marketing.py
authapi/providers/google/__init__.py
authapi/providers/google/ads.py
authapi/providers/google/google.py
authapi/providers/microsoft/__init__.py
authapi/providers/microsoft/bing_ads.py
authapi/providers/microsoft/microsoft.py
authapi/templates/index.html
authapi-0.1.15.dist-info/LICENSE
authapi-0.1.15.dist-info/WHEEL
authapi-0.1.15.dist-info/METADATA
authapi-0.1.15.dist-info/RECORD
